awcc/__init__.py
awcc/__main__.py
awcc/awcc_fs.py
awcc/cli.py
awcc/compile.py
awcc/config.py
awcc/hasher.py
awcc/recipes.py
awcc/reconstruct.py
awcc-0.2.3.1.dist-info/LICENSE
awcc-0.2.3.1.dist-info/METADATA
awcc-0.2.3.1.dist-info/WHEEL
awcc-0.2.3.1.dist-info/entry_points.txt
awcc-0.2.3.1.dist-info/RECORD
