Metadata-Version: 2.3
Name: awcc
Version: 0.2.3.1
Summary: 
License: GNU GENERAL PUBLIC LICENSE
Author: TrollMii
Author-email: trollmii@outlook.de
Requires-Python: >=3.12
Classifier: License :: Other/Proprietary License
Classifier: Programming Language :: Python :: 3
Classifier: Programming Language :: Python :: 3.12
Classifier: Programming Language :: Python :: 3.13
